kahless/__init__.py
kahless/api.py
kahless/middleware.py
kahless/response.py
kahless-0.1.dist-info/LICENSE
kahless-0.1.dist-info/WHEEL
kahless-0.1.dist-info/METADATA
kahless-0.1.dist-info/RECORD
